{"data":[{"id":"MDExOlB1bGxSZXF1ZXN0Njg4MDE3NTE4","title":"fix Layout","url":"https://github.com/Leaffunder/leafunder-front-end/pull/27","state":"MERGED","mergedBy":{"avatarUrl":"https://avatars.githubusercontent.com/u/37486496?u=eefabf5c939e79a01739b502f4081850e56875d5&v=4","url":"https://github.com/Ysrbolles","login":"Ysrbolles"},"createdAt":"2021-07-12T17:09:18Z","number":27,"changedFiles":19,"additions":93,"deletions":103,"baseRepository":{"name":"leafunder-front-end","url":"https://github.com/Leaffunder/leafunder-front-end","owner":{"avatarUrl":"https://avatars.githubusercontent.com/u/86131686?v=4","login":"Leaffunder","url":"https://github.com/Leaffunder"}}},{"id":"MDExOlB1bGxSZXF1ZXN0Njg3NzMzMTg3","title":"Ysrbolles","url":"https://github.com/Leaffunder/leafunder-front-end/pull/26","state":"MERGED","mergedBy":{"avatarUrl":"https://avatars.githubusercontent.com/u/37486496?u=eefabf5c939e79a01739b502f4081850e56875d5&v=4","url":"https://github.com/Ysrbolles","login":"Ysrbolles"},"createdAt":"2021-07-12T10:57:57Z","number":26,"changedFiles":68,"additions":739,"deletions":1575,"baseRepository":{"name":"leafunder-front-end","url":"https://github.com/Leaffunder/leafunder-front-end","owner":{"avatarUrl":"https://avatars.githubusercontent.com/u/86131686?v=4","login":"Leaffunder","url":"https://github.com/Leaffunder"}}},{"id":"MDExOlB1bGxSZXF1ZXN0Njg3MTk5NDg2","title":"Ysrbolles","url":"https://github.com/Leaffunder/leafunder-front-end/pull/25","state":"MERGED","mergedBy":{"avatarUrl":"https://avatars.githubusercontent.com/u/37486496?u=eefabf5c939e79a01739b502f4081850e56875d5&v=4","url":"https://github.com/Ysrbolles","login":"Ysrbolles"},"createdAt":"2021-07-10T15:30:19Z","number":25,"changedFiles":5,"additions":6,"deletions":22,"baseRepository":{"name":"leafunder-front-end","url":"https://github.com/Leaffunder/leafunder-front-end","owner":{"avatarUrl":"https://avatars.githubusercontent.com/u/86131686?v=4","login":"Leaffunder","url":"https://github.com/Leaffunder"}}},{"id":"MDExOlB1bGxSZXF1ZXN0Njg3MTkwMjUy","title":"Ysrbolles","url":"https://github.com/Leaffunder/leafunder-front-end/pull/24","state":"MERGED","mergedBy":{"avatarUrl":"https://avatars.githubusercontent.com/u/37486496?u=eefabf5c939e79a01739b502f4081850e56875d5&v=4","url":"https://github.com/Ysrbolles","login":"Ysrbolles"},"createdAt":"2021-07-10T14:22:21Z","number":24,"changedFiles":8,"additions":174,"deletions":88,"baseRepository":{"name":"leafunder-front-end","url":"https://github.com/Leaffunder/leafunder-front-end","owner":{"avatarUrl":"https://avatars.githubusercontent.com/u/86131686?v=4","login":"Leaffunder","url":"https://github.com/Leaffunder"}}},{"id":"MDExOlB1bGxSZXF1ZXN0Njg2MjEzOTY4","title":"Ysrbolles","url":"https://github.com/Leaffunder/leafunder-front-end/pull/23","state":"MERGED","mergedBy":{"avatarUrl":"https://avatars.githubusercontent.com/u/37486496?u=eefabf5c939e79a01739b502f4081850e56875d5&v=4","url":"https://github.com/Ysrbolles","login":"Ysrbolles"},"createdAt":"2021-07-08T17:51:43Z","number":23,"changedFiles":3,"additions":21,"deletions":10,"baseRepository":{"name":"leafunder-front-end","url":"https://github.com/Leaffunder/leafunder-front-end","owner":{"avatarUrl":"https://avatars.githubusercontent.com/u/86131686?v=4","login":"Leaffunder","url":"https://github.com/Leaffunder"}}},{"id":"MDExOlB1bGxSZXF1ZXN0Njg2MDk1ODMx","title":"Add Idea Fixed","url":"https://github.com/Leaffunder/leafunder-front-end/pull/22","state":"MERGED","mergedBy":{"avatarUrl":"https://avatars.githubusercontent.com/u/37486496?u=eefabf5c939e79a01739b502f4081850e56875d5&v=4","url":"https://github.com/Ysrbolles","login":"Ysrbolles"},"createdAt":"2021-07-08T15:01:21Z","number":22,"changedFiles":5,"additions":26,"deletions":14,"baseRepository":{"name":"leafunder-front-end","url":"https://github.com/Leaffunder/leafunder-front-end","owner":{"avatarUrl":"https://avatars.githubusercontent.com/u/86131686?v=4","login":"Leaffunder","url":"https://github.com/Leaffunder"}}},{"id":"MDExOlB1bGxSZXF1ZXN0Njg2MDYxMjQw","title":"Edit Step Done","url":"https://github.com/Leaffunder/leafunder-front-end/pull/21","state":"MERGED","mergedBy":{"avatarUrl":"https://avatars.githubusercontent.com/u/37486496?u=eefabf5c939e79a01739b502f4081850e56875d5&v=4","url":"https://github.com/Ysrbolles","login":"Ysrbolles"},"createdAt":"2021-07-08T14:20:03Z","number":21,"changedFiles":5,"additions":196,"deletions":40,"baseRepository":{"name":"leafunder-front-end","url":"https://github.com/Leaffunder/leafunder-front-end","owner":{"avatarUrl":"https://avatars.githubusercontent.com/u/86131686?v=4","login":"Leaffunder","url":"https://github.com/Leaffunder"}}},{"id":"MDExOlB1bGxSZXF1ZXN0Njg1NTcyNjM1","title":"Ysrbolles","url":"https://github.com/Leaffunder/leafunder-front-end/pull/20","state":"MERGED","mergedBy":{"avatarUrl":"https://avatars.githubusercontent.com/u/37486496?u=eefabf5c939e79a01739b502f4081850e56875d5&v=4","url":"https://github.com/Ysrbolles","login":"Ysrbolles"},"createdAt":"2021-07-07T23:21:48Z","number":20,"changedFiles":19,"additions":240,"deletions":325,"baseRepository":{"name":"leafunder-front-end","url":"https://github.com/Leaffunder/leafunder-front-end","owner":{"avatarUrl":"https://avatars.githubusercontent.com/u/86131686?v=4","login":"Leaffunder","url":"https://github.com/Leaffunder"}}},{"id":"MDExOlB1bGxSZXF1ZXN0Njg0NTU4Njgy","title":"Ysrbolles","url":"https://github.com/Leaffunder/leafunder-front-end/pull/19","state":"MERGED","mergedBy":{"avatarUrl":"https://avatars.githubusercontent.com/u/37486496?u=eefabf5c939e79a01739b502f4081850e56875d5&v=4","url":"https://github.com/Ysrbolles","login":"Ysrbolles"},"createdAt":"2021-07-06T17:34:10Z","number":19,"changedFiles":17,"additions":174,"deletions":59,"baseRepository":{"name":"leafunder-front-end","url":"https://github.com/Leaffunder/leafunder-front-end","owner":{"avatarUrl":"https://avatars.githubusercontent.com/u/86131686?v=4","login":"Leaffunder","url":"https://github.com/Leaffunder"}}},{"id":"MDExOlB1bGxSZXF1ZXN0NjgzODYyMDMx","title":"Ysrbolles","url":"https://github.com/Leaffunder/leafunder-front-end/pull/18","state":"MERGED","mergedBy":{"avatarUrl":"https://avatars.githubusercontent.com/u/37486496?u=eefabf5c939e79a01739b502f4081850e56875d5&v=4","url":"https://github.com/Ysrbolles","login":"Ysrbolles"},"createdAt":"2021-07-05T17:55:49Z","number":18,"changedFiles":15,"additions":254,"deletions":63,"baseRepository":{"name":"leafunder-front-end","url":"https://github.com/Leaffunder/leafunder-front-end","owner":{"avatarUrl":"https://avatars.githubusercontent.com/u/86131686?v=4","login":"Leaffunder","url":"https://github.com/Leaffunder"}}},{"id":"MDExOlB1bGxSZXF1ZXN0NjgzNjM3NjIy","title":"Ysrbolles","url":"https://github.com/Leaffunder/leafunder-front-end/pull/17","state":"MERGED","mergedBy":{"avatarUrl":"https://avatars.githubusercontent.com/u/37486496?u=eefabf5c939e79a01739b502f4081850e56875d5&v=4","url":"https://github.com/Ysrbolles","login":"Ysrbolles"},"createdAt":"2021-07-05T11:55:48Z","number":17,"changedFiles":6,"additions":58,"deletions":23,"baseRepository":{"name":"leafunder-front-end","url":"https://github.com/Leaffunder/leafunder-front-end","owner":{"avatarUrl":"https://avatars.githubusercontent.com/u/86131686?v=4","login":"Leaffunder","url":"https://github.com/Leaffunder"}}},{"id":"MDExOlB1bGxSZXF1ZXN0NjgzMDc5NDY0","title":"Ysrbolles","url":"https://github.com/Leaffunder/leafunder-front-end/pull/16","state":"MERGED","mergedBy":{"avatarUrl":"https://avatars.githubusercontent.com/u/37486496?u=eefabf5c939e79a01739b502f4081850e56875d5&v=4","url":"https://github.com/Ysrbolles","login":"Ysrbolles"},"createdAt":"2021-07-03T21:24:46Z","number":16,"changedFiles":11,"additions":278,"deletions":78,"baseRepository":{"name":"leafunder-front-end","url":"https://github.com/Leaffunder/leafunder-front-end","owner":{"avatarUrl":"https://avatars.githubusercontent.com/u/86131686?v=4","login":"Leaffunder","url":"https://github.com/Leaffunder"}}},{"id":"MDExOlB1bGxSZXF1ZXN0NjEzNjg3MTgw","title":"Manage Team Redesign 80%","url":"https://github.com/Leaffunder/leafunder-front-end/pull/11","state":"MERGED","mergedBy":{"avatarUrl":"https://avatars.githubusercontent.com/u/37486496?u=eefabf5c939e79a01739b502f4081850e56875d5&v=4","url":"https://github.com/Ysrbolles","login":"Ysrbolles"},"createdAt":"2021-04-12T14:37:18Z","number":11,"changedFiles":12,"additions":170,"deletions":125,"baseRepository":{"name":"leafunder-front-end","url":"https://github.com/Leaffunder/leafunder-front-end","owner":{"avatarUrl":"https://avatars.githubusercontent.com/u/86131686?v=4","login":"Leaffunder","url":"https://github.com/Leaffunder"}}},{"id":"MDExOlB1bGxSZXF1ZXN0NTMzMDI3NDY3","title":"Slaanani","url":"https://github.com/Leaffunder/leafunder-front-end/pull/1","state":"MERGED","mergedBy":{"avatarUrl":"https://avatars.githubusercontent.com/u/43524489?u=22e1cbf7acdb373370cb95cd381c9576e5f8c299&v=4","url":"https://github.com/Imgox","login":"Imgox"},"createdAt":"2020-12-05T14:46:59Z","number":1,"changedFiles":81,"additions":41534,"deletions":104,"baseRepository":{"name":"leafunder-front-end","url":"https://github.com/Leaffunder/leafunder-front-end","owner":{"avatarUrl":"https://avatars.githubusercontent.com/u/86131686?v=4","login":"Leaffunder","url":"https://github.com/Leaffunder"}}},{"id":"MDExOlB1bGxSZXF1ZXN0MzAxNzE1Njc4","title":"index.html","url":"https://github.com/khaoulazouggar/roger_skyline/pull/1","state":"CLOSED","mergedBy":null,"createdAt":"2019-07-26T23:53:30Z","number":1,"changedFiles":1,"additions":1,"deletions":1,"baseRepository":{"name":"roger_skyline","url":"https://github.com/khaoulazouggar/roger_skyline","owner":{"avatarUrl":"https://avatars.githubusercontent.com/u/47794335?u=52dd2893dbf54d7457dca5644476ea01fdcb93a9&v=4","login":"khaoulazouggar","url":"https://github.com/khaoulazouggar"}}}],"open":0,"closed":1,"merged":14,"totalCount":15}